<?xml version="1.0" encoding="UTF-8"?>
<beans xmlns="http://www.springframework.org/schema/beans"
       xmlns:xsi="http://www.w3.org/2001/XMLSchema-instance"
       xmlns:util="http://www.springframework.org/schema/util" xsi:schemaLocation="
        http://www.springframework.org/schema/beans http://www.springframework.org/schema/beans/spring-beans.xsd
        http://www.springframework.org/schema/util http://www.springframework.org/schema/util/spring-util.xsd"> <!-- bean definitions here -->

    <bean id="userDataBaseProvider" class="com.loose.coupling.UserDatabaseProvider">

    </bean>

    <bean id="webServiceDataProvider" class="com.loose.coupling.WebServiceDataProvider">

    </bean>

    <bean id="newDataBaseProvider" class="com.loose.coupling.NewDatabaseProvider">

    </bean>

    <bean id="userManager" class="com.loose.coupling.UserManager">
        <constructor-arg ref="newDataBaseProvider"/>
    </bean>
</beans>